ymscript.py
ymscript-22.dist-info/METADATA
ymscript-22.dist-info/WHEEL
ymscript-22.dist-info/top_level.txt
ymscript-22.dist-info/RECORD
