Metadata-Version: 2.4
Name: ymscript
Version: 22
Summary: Image Processing Scripts
Home-page: https://git.sr.ht/~coco/ymscript
Author: Enric Meinhardt-Llopis
Author-email: enric.meinhardt@fastmail.com
License: AGPL-3.0
Classifier: Operating System :: OS Independent
Classifier: Topic :: Scientific/Engineering :: Image Processing
Classifier: Topic :: Scientific/Engineering :: Mathematics
Dynamic: author
Dynamic: author-email
Dynamic: classifier
Dynamic: home-page
Dynamic: license
Dynamic: summary
